proj2pdf/__init__.py
proj2pdf/cli.py
proj2pdf/converters.py
proj2pdf-0.1.0.dist-info/licenses/LICENSE
proj2pdf-0.1.0.dist-info/METADATA
proj2pdf-0.1.0.dist-info/WHEEL
proj2pdf-0.1.0.dist-info/entry_points.txt
proj2pdf-0.1.0.dist-info/top_level.txt
proj2pdf-0.1.0.dist-info/RECORD
