Metadata-Version: 2.4
Name: proj2pdf
Version: 0.1.0
Summary: A CLI tool to convert project files to PDF
Author-email: Gordon Oh <gordonoh@yahoo.com.sg>
License: MIT License
Project-URL: Homepage, https://github.com/gordonjun2/proj2pdf
Classifier: Development Status :: 3 - Alpha
Classifier: Intended Audience :: Developers
Classifier: Operating System :: OS Independent
Classifier: Programming Language :: Python :: 3
Classifier: Programming Language :: Python :: 3.7
Classifier: Programming Language :: Python :: 3.8
Classifier: Programming Language :: Python :: 3.9
Classifier: Programming Language :: Python :: 3.10
Classifier: Programming Language :: Python :: 3.11
Requires-Python: >=3.7
License-File: LICENSE
Requires-Dist: nbformat>=5.7.0
Requires-Dist: nbconvert>=7.2.0
Requires-Dist: playwright>=1.39.0
Requires-Dist: markdownify>=0.11.6
Requires-Dist: weasyprint==60.1
Requires-Dist: PyPDF2>=3.0.0
Requires-Dist: jupyter>=1.0.0
Requires-Dist: Pygments>=2.17.2
Dynamic: license-file
